MANIFEST.in
README.md
setup.py
pystlogo/__init__.py
pystlogo/error.py
pystlogo.egg-info/PKG-INFO
pystlogo.egg-info/SOURCES.txt
pystlogo.egg-info/dependency_links.txt
pystlogo.egg-info/requires.txt
pystlogo.egg-info/top_level.txt