Metadata-Version: 1.1
Name: pystlogo
Version: 0.0.1
Summary: A Python package to generate simple logos
Home-page: https://github.com/Sithijatd/pystlogo
Author: Sithijatd
Author-email: Sithijatd@users.noreply.github.com
License: MIT
Keywords: Telegram,python,logo,anime
Platform: UNKNOWN
Classifier: Development Status :: 5 - Production/Stable
Classifier: Intended Audience :: Education
Classifier: Operating System :: Microsoft :: Windows :: Windows 10
Classifier: License :: OSI Approved :: MIT License
Classifier: Programming Language :: Python :: 3
Classifier: Programming Language :: Python :: 3.4
Classifier: Programming Language :: Python :: 3.5
Classifier: Programming Language :: Python :: 3.6
Classifier: Programming Language :: Python :: 3.9
Classifier: Programming Language :: Python :: 3.10
